xcom_attr_assigner_mixin/__init__.py
xcom_attr_assigner_mixin/xcom_attr_assigner_mixin.py
amsterdam_airflow_xcom_attr_assigner_mixin-1.0.dist-info/WHEEL
amsterdam_airflow_xcom_attr_assigner_mixin-1.0.dist-info/METADATA
amsterdam_airflow_xcom_attr_assigner_mixin-1.0.dist-info/RECORD
